Workbook
Name Rendimento_Mensal: Simulador!$D$13:$D$13

Sheet Simulador
B11: Configurações
B12: Salario | D12: 5000
B13: Rendimento Carteira | D13: 0.008
B14: Sugestão Investimento | D14: =D12 * 30% -> 1500
B16: Investimento Mensal
B17: Quanto investir por mês? | D17: 500
B18: Por quantos anos? | D18: 5
B19: Taxa de rendimento mensal? | D19: 0.01079
B20: Patrimônio acumulado? | D20: =FV(D19,D18*12,D17*-1) -> 41888.457
B21: Dividendos mensais? | D21: =D20*$D$13 -> 335.10766
B23: Cenários | D23: Dividendos
A24: 2 | B24: Quanto em 2 anos? | C24: =FV($D$19,$A24*12,$D$17*-1) -> 13613.814 | D24: =C24*$D$13 -> 108.91051
A25: 5 | B25: Quanto em 5 anos? | C25: =FV($D$19,$A25*12,$D$17*-1) -> 41888.457 | D25: =C25*$D$13 -> 335.10766
A26: 10 | B26: Quanto em 10 anos? | C26: =FV($D$19,$A26*12,$D$17*-1) -> 121642.11 | D26: =C26*$D$13 -> 973.13685
A27: 20 | B27: Quanto em 20 anos? | C27: =FV($D$19,$A27*12,$D$17*-1) -> 562599.2 | D27: =C27*$D$13 -> 4500.7936
A28: 30 | B28: Quanto em 30 anos? | C28: =FV($D$19,$A28*12,$D$17*-1) -> 2161084.8 | D28: =C28*$D$13 -> 17288.679
B32: Perfil | C32: Moderado
B33: Valor a ser investido por mês | C33: 500
B35: Tipos de FII | C35: Percentual Sugerido | D35: Valores
B36: Papel | C36: =VLOOKUP($C$32&"-"&B36,'Planilha Apoio'!$A3:$D21,4,FALSE) -> 0.32 | D36: =$C$33*C36 -> 160
B37: Tijolo | C37: =VLOOKUP($C$32&"-"&B37,'Planilha Apoio'!$A4:$D22,4,FALSE) -> 0.35 | D37: =$C$33*C37 -> 175
B38: Hibridos | C38: =VLOOKUP($C$32&"-"&B38,'Planilha Apoio'!$A5:$D23,4,FALSE) -> 0.08 | D38: =$C$33*C38 -> 40
B39: Fofs | C39: =VLOOKUP($C$32&"-"&B39,'Planilha Apoio'!$A6:$D24,4,FALSE) -> 0.05 | D39: =$C$33*C39 -> 25
B40: Desenvolvimento | C40: =VLOOKUP($C$32&"-"&B40,'Planilha Apoio'!$A7:$D25,4,FALSE) -> 0.1 | D40: =$C$33*C40 -> 50
B41: Hotelaria | C41: =VLOOKUP($C$32&"-"&B41,'Planilha Apoio'!$A8:$D26,4,FALSE) -> 0.1 | D41: =$C$33*C41 -> 50
D42: =SUM(D36:D41) -> 500

Sheet Planilha Apoio
A3: Chave | B3: Perfil | C3: Tipo FII | D3: %
A4: =B4&"-"&C4 -> Conservador-Papel | B4: Conservador | C4: Papel | D4: 0.3
A5: =B5&"-"&C5 -> Conservador-Tijolo | B5: Conservador | C5: Tijolo | D5: 0.5
A6: =B6&"-"&C6 -> Conservador-Hibridos | B6: Conservador | C6: Hibridos | D6: 0.1
A7: =B7&"-"&C7 -> Conservador-Fofs | B7: Conservador | C7: Fofs | D7: 0.1 | F7: Moderado-Papel | G7: =VLOOKUP(F7,$A3:$D21,4,FALSE) -> 0.32
A8: =B8&"-"&C8 -> Conservador-Desenvolvimento | B8: Conservador | C8: Desenvolvimento | D8: 0
A9: =B9&"-"&C9 -> Conservador-Hotelaria | B9: Conservador | C9: Hotelaria | D9: 0
A10: =B10&"-"&C10 -> Moderado-Papel | B10: Moderado | C10: Papel | D10: 0.32
A11: =B11&"-"&C11 -> Moderado-Tijolo | B11: Moderado | C11: Tijolo | D11: 0.35
A12: =B12&"-"&C12 -> Moderado-Hibridos | B12: Moderado | C12: Hibridos | D12: 0.08
A13: =B13&"-"&C13 -> Moderado-Fofs | B13: Moderado | C13: Fofs | D13: 0.05
A14: =B14&"-"&C14 -> Moderado-Desenvolvimento | B14: Moderado | C14: Desenvolvimento | D14: 0.1
A15: =B15&"-"&C15 -> Moderado-Hotelaria | B15: Moderado | C15: Hotelaria | D15: 0.1
A16: =B16&"-"&C16 -> Agressivo-Papel | B16: Agressivo | C16: Papel | D16: 0.5
A17: =B17&"-"&C17 -> Agressivo-Tijolo | B17: Agressivo | C17: Tijolo | D17: 0.1
A18: =B18&"-"&C18 -> Agressivo-Hibridos | B18: Agressivo | C18: Hibridos | D18: 0.05
A19: =B19&"-"&C19 -> Agressivo-Fofs | B19: Agressivo | C19: Fofs | D19: 0.05
... A21: =B21&"-"&C21 -> Agressivo-Hotelaria | B21: Agressivo | C21: Hotelaria | D21: 0.1
